bioinf_common/__init__.py
bioinf_common/algorithms/__init__.py
bioinf_common/algorithms/cluster_separation.py
bioinf_common/algorithms/cluster_separation_cpp.cpython-37m-darwin.so
bioinf_common/algorithms/network_coherence.py
bioinf_common/algorithms/network_coherence_cpp.cpython-37m-darwin.so
bioinf_common/algorithms/network_walks.py
bioinf_common/algorithms/set_enrichment.py
bioinf_common/data_reader/__init__.py
bioinf_common/data_reader/biogrid.py
bioinf_common/data_reader/cosmic.py
bioinf_common/data_reader/go.py
bioinf_common/data_reader/kegg.py
bioinf_common/data_reader/msigdb.py
bioinf_common/data_reader/stringdb.py
bioinf_common/plotting/__init__.py
bioinf_common/plotting/grid_plots.py
bioinf_common/plotting/statistics_plot.py
bioinf_common/plotting/utils.py
bioinf_common/statistics/__init__.py
bioinf_common/statistics/fitting.py
bioinf_common/tests/__init__.py
bioinf_common/tests/test_chunk_parallelization.py
bioinf_common/tests/test_cluster_separation.py
bioinf_common/tests/test_cpp_utils.py
bioinf_common/tests/test_cpptype_converters.py
bioinf_common/tests/test_datastructure_conversion.py
bioinf_common/tests/test_fitting.py
bioinf_common/tests/test_graph_tool_wrapper.py
bioinf_common/tests/test_misc.py
bioinf_common/tests/test_network_coherence.py
bioinf_common/tests/test_set_enrichments.py
bioinf_common/tools/__init__.py
bioinf_common/tools/cpp_utils.cpython-37m-darwin.so
bioinf_common/tools/datastructure_conversion.py
bioinf_common/tools/graph_tool_wrapper.py
bioinf_common/tools/list_chunk_parallelization.py
bioinf_common/tools/misc.py
bioinf_common-0.0.3.data/scripts/exec_ipynb
bioinf_common-0.0.3.data/scripts/watch_process
bioinf_common-0.0.3.dist-info/METADATA
bioinf_common-0.0.3.dist-info/WHEEL
bioinf_common-0.0.3.dist-info/top_level.txt
bioinf_common-0.0.3.dist-info/RECORD
