Metadata-Version: 2.1
Name: bioinf-common
Version: 0.0.3
Summary: Aggregation of functionalities needed in multiple projects
Home-page: UNKNOWN
Author: kpj
Author-email: kpjkpjkpjkpjkpjkpj@gmail.com
License: UNKNOWN
Platform: UNKNOWN
Requires-Dist: numpy
Requires-Dist: pandas
Requires-Dist: networkx
Requires-Dist: dask[complete]
Requires-Dist: scipy
Requires-Dist: statsmodels
Requires-Dist: gene-map
Requires-Dist: obonet
Requires-Dist: matplotlib
Requires-Dist: seaborn
Requires-Dist: tqdm
Requires-Dist: joblib
Requires-Dist: bs4
Requires-Dist: jupyter
Requires-Dist: click
Requires-Dist: psutil
Requires-Dist: pybind11
Requires-Dist: nbformat
Requires-Dist: nbconvert
Requires-Dist: mypy-extensions
